zor/__init__.py
zor/api.py
zor/config.py
zor/context.py
zor/file_ops.py
zor/git_utils.py
zor/history.py
zor/main.py
zor/safety.py
zor/prompts/file_generation.txt
zor/prompts/generate_test_prompt.txt
zor/prompts/planning_prompt.txt
zor/prompts/refactor_prompt.txt
zor/prompts/zor_ascii.txt
zor-0.0.6.dist-info/licenses/LICENSE
zor-0.0.6.dist-info/METADATA
zor-0.0.6.dist-info/WHEEL
zor-0.0.6.dist-info/entry_points.txt
zor-0.0.6.dist-info/top_level.txt
zor-0.0.6.dist-info/RECORD
