Metadata-Version: 2.4
Name: zor
Version: 0.0.6
Summary: An Open-Source Claude Code like tool
Author-email: Hemanth <arjunbanur27@gmail.com>
License: MIT License
Project-URL: Homepage, https://github.com/arjuuuuunnnnn/zor
Project-URL: Bug Tracker, https://github.com/arjuuuuunnnnn/zor/issues
Keywords: ai,code,assistant,gemini,development
Classifier: Development Status :: 3 - Alpha
Classifier: Intended Audience :: Developers
Classifier: License :: OSI Approved :: MIT License
Classifier: Programming Language :: Python :: 3
Classifier: Programming Language :: Python :: 3.9
Classifier: Programming Language :: Python :: 3.10
Classifier: Programming Language :: Python :: 3.11
Classifier: Programming Language :: Python :: 3.12
Classifier: Programming Language :: Python :: 3.13
Requires-Python: >=3.9
License-File: LICENSE
Requires-Dist: google-generativeai==0.8.4
Requires-Dist: python-dotenv==1.1.0
Requires-Dist: typer==0.15.2
Requires-Dist: rich==14.0.0
Requires-Dist: pygments==2.19.1
Requires-Dist: tqdm==4.67.1
Dynamic: license-file
